miniops/__init__.py
miniops/agent.py
miniops/utils.py
miniops-0.1.17.dist-info/LICENSE
miniops-0.1.17.dist-info/WHEEL
miniops-0.1.17.dist-info/METADATA
miniops-0.1.17.dist-info/RECORD
