Metadata-Version: 2.1
Name: miniops
Version: 0.1.17
Summary: python package to efficiently work with dataframes from jsonl files stored at minio/s3
Author: Federico Falconieri
Author-email: federico.falconieri@tno.nl
Requires-Python: >=3.9,<4.0
Classifier: Programming Language :: Python :: 3
Classifier: Programming Language :: Python :: 3.10
Classifier: Programming Language :: Python :: 3.9
Requires-Dist: minio (>=7.1.8,<8.0.0)
Requires-Dist: pandas (>=1.4.2,<2.0.0)
Requires-Dist: psutil (>=5.9.1,<6.0.0)
